{
    "uid": "77f61222-c96a-4225-9e62-3d3b33dba791",
    "name": "51_Xgboost",
    "preprocessing": [
        {
            "categorical_y": {
                "0.12": 0,
                "0.403": 1,
                "0.597": 2,
                "15.0": 3,
                "62.0": 4,
                "79.0": 5,
                "458.0": 6,
                "758.0": 7,
                "805.0": 8,
                "3173.0": 9,
                "4246.0": 10,
                "5381.0": 11,
                "10237.0": 12,
                "11991.0": 13,
                "16429.0": 14,
                "18358.0": 15,
                "35074.0": 16,
                "51901.0": 17,
                "76738.0": 18,
                "86975.0": 19
            },
            "ml_task": "multiclass_classification",
            "params": {
                "columns_preprocessing": {},
                "target_preprocessing": [
                    "na_exclude",
                    "categorical_to_int"
                ],
                "ml_task": "multiclass_classification"
            }
        },
        {
            "categorical_y": {
                "0.12": 0,
                "0.403": 1,
                "0.597": 2,
                "15.0": 3,
                "62.0": 4,
                "79.0": 5,
                "458.0": 6,
                "758.0": 7,
                "805.0": 8,
                "3173.0": 9,
                "4246.0": 10,
                "5381.0": 11,
                "10237.0": 12,
                "11991.0": 13,
                "16429.0": 14,
                "18358.0": 15,
                "35074.0": 16,
                "51901.0": 17,
                "76738.0": 18,
                "86975.0": 19
            },
            "ml_task": "multiclass_classification",
            "params": {
                "columns_preprocessing": {},
                "target_preprocessing": [
                    "na_exclude",
                    "categorical_to_int"
                ],
                "ml_task": "multiclass_classification"
            }
        },
        {
            "categorical_y": {
                "0.12": 0,
                "0.403": 1,
                "0.597": 2,
                "15.0": 3,
                "62.0": 4,
                "79.0": 5,
                "458.0": 6,
                "758.0": 7,
                "805.0": 8,
                "3173.0": 9,
                "4246.0": 10,
                "5381.0": 11,
                "10237.0": 12,
                "11991.0": 13,
                "16429.0": 14,
                "18358.0": 15,
                "35074.0": 16,
                "51901.0": 17,
                "76738.0": 18,
                "86975.0": 19
            },
            "ml_task": "multiclass_classification",
            "params": {
                "columns_preprocessing": {},
                "target_preprocessing": [
                    "na_exclude",
                    "categorical_to_int"
                ],
                "ml_task": "multiclass_classification"
            }
        },
        {
            "categorical_y": {
                "0.12": 0,
                "0.403": 1,
                "0.597": 2,
                "15.0": 3,
                "62.0": 4,
                "79.0": 5,
                "458.0": 6,
                "758.0": 7,
                "805.0": 8,
                "3173.0": 9,
                "4246.0": 10,
                "5381.0": 11,
                "10237.0": 12,
                "11991.0": 13,
                "16429.0": 14,
                "18358.0": 15,
                "35074.0": 16,
                "51901.0": 17,
                "76738.0": 18,
                "86975.0": 19
            },
            "ml_task": "multiclass_classification",
            "params": {
                "columns_preprocessing": {},
                "target_preprocessing": [
                    "na_exclude",
                    "categorical_to_int"
                ],
                "ml_task": "multiclass_classification"
            }
        },
        {
            "categorical_y": {
                "0.12": 0,
                "0.403": 1,
                "0.597": 2,
                "15.0": 3,
                "62.0": 4,
                "79.0": 5,
                "458.0": 6,
                "758.0": 7,
                "805.0": 8,
                "3173.0": 9,
                "4246.0": 10,
                "5381.0": 11,
                "10237.0": 12,
                "11991.0": 13,
                "16429.0": 14,
                "18358.0": 15,
                "35074.0": 16,
                "51901.0": 17,
                "76738.0": 18,
                "86975.0": 19
            },
            "ml_task": "multiclass_classification",
            "params": {
                "columns_preprocessing": {},
                "target_preprocessing": [
                    "na_exclude",
                    "categorical_to_int"
                ],
                "ml_task": "multiclass_classification"
            }
        }
    ],
    "learners": [
        {
            "library_version": "1.7.1",
            "algorithm_name": "Extreme Gradient Boosting",
            "algorithm_short_name": "Xgboost",
            "uid": "d53371cc-c89a-4f8d-bae4-5174642c0646",
            "params": {
                "model_type": "Xgboost",
                "ml_task": "multiclass_classification",
                "n_jobs": -1,
                "objective": "multi:softprob",
                "eta": 0.1,
                "max_depth": 6,
                "min_child_weight": 1,
                "subsample": 1.0,
                "colsample_bytree": 1.0,
                "seed": 3,
                "eval_metric": "mlogloss",
                "num_class": 20,
                "explain_level": 1
            },
            "name": "learner_fold_0",
            "best_ntree_limit": 306
        },
        {
            "library_version": "1.7.1",
            "algorithm_name": "Extreme Gradient Boosting",
            "algorithm_short_name": "Xgboost",
            "uid": "d2dd9db8-aef8-4642-8519-5603459c19c5",
            "params": {
                "model_type": "Xgboost",
                "ml_task": "multiclass_classification",
                "n_jobs": -1,
                "objective": "multi:softprob",
                "eta": 0.1,
                "max_depth": 6,
                "min_child_weight": 1,
                "subsample": 1.0,
                "colsample_bytree": 1.0,
                "seed": 3,
                "eval_metric": "mlogloss",
                "num_class": 20,
                "explain_level": 1
            },
            "name": "learner_fold_1",
            "best_ntree_limit": 306
        },
        {
            "library_version": "1.7.1",
            "algorithm_name": "Extreme Gradient Boosting",
            "algorithm_short_name": "Xgboost",
            "uid": "d20ed29b-55f6-462e-b380-b1e2f4bccec5",
            "params": {
                "model_type": "Xgboost",
                "ml_task": "multiclass_classification",
                "n_jobs": -1,
                "objective": "multi:softprob",
                "eta": 0.1,
                "max_depth": 6,
                "min_child_weight": 1,
                "subsample": 1.0,
                "colsample_bytree": 1.0,
                "seed": 3,
                "eval_metric": "mlogloss",
                "num_class": 20,
                "explain_level": 1
            },
            "name": "learner_fold_2",
            "best_ntree_limit": 306
        },
        {
            "library_version": "1.7.1",
            "algorithm_name": "Extreme Gradient Boosting",
            "algorithm_short_name": "Xgboost",
            "uid": "4a030333-c6d4-4dec-9583-e92e1be8df32",
            "params": {
                "model_type": "Xgboost",
                "ml_task": "multiclass_classification",
                "n_jobs": -1,
                "objective": "multi:softprob",
                "eta": 0.1,
                "max_depth": 6,
                "min_child_weight": 1,
                "subsample": 1.0,
                "colsample_bytree": 1.0,
                "seed": 3,
                "eval_metric": "mlogloss",
                "num_class": 20,
                "explain_level": 1
            },
            "name": "learner_fold_3",
            "best_ntree_limit": 306
        },
        {
            "library_version": "1.7.1",
            "algorithm_name": "Extreme Gradient Boosting",
            "algorithm_short_name": "Xgboost",
            "uid": "b8a3ad2f-541a-41f9-bed7-e899bbc11d34",
            "params": {
                "model_type": "Xgboost",
                "ml_task": "multiclass_classification",
                "n_jobs": -1,
                "objective": "multi:softprob",
                "eta": 0.1,
                "max_depth": 6,
                "min_child_weight": 1,
                "subsample": 1.0,
                "colsample_bytree": 1.0,
                "seed": 3,
                "eval_metric": "mlogloss",
                "num_class": 20,
                "explain_level": 1
            },
            "name": "learner_fold_4",
            "best_ntree_limit": 306
        }
    ],
    "params": {
        "additional": {
            "max_rounds": 10000,
            "early_stopping_rounds": 50,
            "max_rows_limit": null,
            "max_cols_limit": null
        },
        "preprocessing": {
            "columns_preprocessing": {},
            "target_preprocessing": [
                "na_exclude",
                "categorical_to_int"
            ],
            "ml_task": "multiclass_classification"
        },
        "validation_strategy": {
            "validation_type": "kfold",
            "k_folds": 5,
            "shuffle": true,
            "stratify": true,
            "X_path": "AutoML_10\\X.data",
            "y_path": "AutoML_10\\y.data",
            "results_path": "AutoML_10"
        },
        "learner": {
            "model_type": "Xgboost",
            "ml_task": "multiclass_classification",
            "n_jobs": -1,
            "objective": "multi:softprob",
            "eta": 0.1,
            "max_depth": 6,
            "min_child_weight": 1,
            "subsample": 1.0,
            "colsample_bytree": 1.0,
            "seed": 3,
            "eval_metric": "mlogloss",
            "num_class": 20,
            "explain_level": 1
        },
        "automl_random_state": 1234,
        "ml_task": "multiclass_classification",
        "explain_level": 1,
        "name": "51_Xgboost",
        "status": "initialized",
        "final_loss": null,
        "train_time": null,
        "data_type": "original",
        "max_time_for_learner": 72.0
    },
    "saved": [
        "51_Xgboost\\learner_fold_0.xgboost",
        "51_Xgboost\\learner_fold_1.xgboost",
        "51_Xgboost\\learner_fold_2.xgboost",
        "51_Xgboost\\learner_fold_3.xgboost",
        "51_Xgboost\\learner_fold_4.xgboost"
    ],
    "predictions_fname": "51_Xgboost\\predictions_out_of_folds.csv",
    "metric_name": "logloss",
    "final_loss": 0.03944363538175821,
    "train_time": 24.527002573013306,
    "is_stacked": false,
    "single_prediction_time": 0.02200150489807129
}